edgegap_migrate/__init__.py
edgegap_migrate-1.6.1.dist-info/LICENSE
edgegap_migrate-1.6.1.dist-info/METADATA
edgegap_migrate-1.6.1.dist-info/WHEEL
edgegap_migrate-1.6.1.dist-info/RECORD
