Metadata-Version: 2.1
Name: edgegap-migrate
Version: 1.6.1
Summary: The Edgegap library to handle migrations. It is designed for use within the Edgegap organization.
Author: Bastien Roy
Author-email: bastien@edgegap.com
Requires-Python: >=3.10,<4.0
Classifier: Programming Language :: Python :: 3
Classifier: Programming Language :: Python :: 3.10
Classifier: Programming Language :: Python :: 3.11
Requires-Dist: console-menu (>=0.8.0,<0.9.0)
Requires-Dist: edgegap-logging (>=1.2.0,<2.0.0)
